{"g025200":{"bCode":"bw0252","displayName":"SCHELLINGSTR. 7  ","buildingPart":"bt0252","mapUri":"0252_d_00.pdf","level":"EG","fName":"Erdgeschoss","mapSizeX":"3508","mapSizeY":"2479","address":"Schellingstr. 07"},"g025201":{"bCode":"bw0252","displayName":"SCHELLINGSTR. 7  ","buildingPart":"bt0252","mapUri":"0252_d_01.pdf","level":"OG 01","fName":"1.Obergeschoss","mapSizeX":"3508","mapSizeY":"2479","address":"Schellingstr. 07"},"g025202":{"bCode":"bw0252","displayName":"SCHELLINGSTR. 7  ","buildingPart":"bt0252","mapUri":"0252_d_02.pdf","level":"OG 02","fName":"2.Obergeschoss","mapSizeX":"3508","mapSizeY":"2479","address":"Schellingstr. 07"},"g025203":{"bCode":"bw0252","displayName":"SCHELLINGSTR. 7  ","buildingPart":"bt0252","mapUri":"0252_d_03.pdf","level":"OG 03","fName":"3.Obergeschoss","mapSizeX":"3508","mapSizeY":"2479","address":"Schellingstr. 07"}}