[{"bCode":"bw0650","displayName":"KONRADSTR. 6","fCode":"g065000","buildingPart":"bt0650","level":"EG","fName":"Erdgeschoss","mapUri":"0650_d_00.pdf","mapSizeX":"3508","mapSizeY":"2479","address":"Konradstr. 06"},{"bCode":"bw0650","displayName":"KONRADSTR. 6","fCode":"g065001","buildingPart":"bt0650","level":"OG 01","fName":"1.Obergeschoss","mapUri":"0650_d_01.pdf","mapSizeX":"3508","mapSizeY":"2479","address":"Konradstr. 06"},{"bCode":"bw0650","displayName":"KONRADSTR. 6","fCode":"g065002","buildingPart":"bt0650","level":"OG 02","fName":"2.Obergeschoss","mapUri":"0650_d_02.pdf","mapSizeX":"3508","mapSizeY":"2479","address":"Konradstr. 06"},{"bCode":"bw0650","displayName":"KONRADSTR. 6","fCode":"g065003","buildingPart":"bt0650","level":"OG 03","fName":"3.Obergeschoss","mapUri":"0650_d_03.pdf","mapSizeX":"3508","mapSizeY":"2479","address":"Konradstr. 06"},{"bCode":"bw0650","displayName":"KONRADSTR. 6","fCode":"g065004","buildingPart":"bt0650","level":"OG 04","fName":"4.Obergeschoss","mapUri":"0650_d_04.pdf","mapSizeX":"3508","mapSizeY":"2479","address":"Konradstr. 06"},{"bCode":"bw0650","displayName":"KONRADSTR. 6","fCode":"g0650-1","buildingPart":"bt0650","level":"UG 01","fName":"1.Untergeschoss","mapUri":"0650_d_u1.pdf","mapSizeX":"3508","mapSizeY":"2479","address":"Konradstr. 06"}]