[{"bCode":"bw1500","displayName":"PETTENKOFERSTR. 12","fCode":"g150000","buildingPart":"bt1500","level":"EG","fName":"Erdgeschoss","mapUri":"1508_d_00.pdf","mapSizeX":"3508","mapSizeY":"2479","address":"Pettenkoferstr. 12 (E)"},{"bCode":"bw1500","displayName":"PETTENKOFERSTR. 12","fCode":"g150001","buildingPart":"bt1500","level":"OG 01","fName":"1.Obergeschoss","mapUri":"1508_d_01.pdf","mapSizeX":"3508","mapSizeY":"2479","address":"Pettenkoferstr. 12 (E)"},{"bCode":"bw1500","displayName":"PETTENKOFERSTR. 12","fCode":"g150002","buildingPart":"bt1500","level":"OG 02","fName":"2.Obergeschoss","mapUri":"1508_d_02.pdf","mapSizeX":"3508","mapSizeY":"2479","address":"Pettenkoferstr. 12 (E)"},{"bCode":"bw1500","displayName":"PETTENKOFERSTR. 12","fCode":"g150003","buildingPart":"bt1500","level":"OG 03","fName":"3.Obergeschoss","mapUri":"1508_d_03.pdf","mapSizeX":"3508","mapSizeY":"2479","address":"Pettenkoferstr. 12 (E)"},{"bCode":"bw1500","displayName":"PETTENKOFERSTR. 12","fCode":"g1500-1","buildingPart":"bt1500","level":"UG 01","fName":"1.Untergeschoss","mapUri":"1508_d_u1.pdf","mapSizeX":"3508","mapSizeY":"2479","address":"Pettenkoferstr. 12 (E)"}]